poshare/__init__.py
poshare/guoren.py
poshare/po.py
poshare/xueqiu.py
poshare-0.3.0.dist-info/METADATA
poshare-0.3.0.dist-info/WHEEL
poshare-0.3.0.dist-info/RECORD
