Metadata-Version: 2.1
Name: poshare
Version: 0.3.0
Summary: 
Author: pluto
Author-email: mayuanchi1029@gmail.com
Requires-Python: >=3.8,<4.0
Classifier: Programming Language :: Python :: 3
Classifier: Programming Language :: Python :: 3.8
Classifier: Programming Language :: Python :: 3.9
Classifier: Programming Language :: Python :: 3.10
Classifier: Programming Language :: Python :: 3.11
Requires-Dist: Js2Py (>=0.74,<0.75)
Requires-Dist: beautifulsoup4 (>=4.12.2,<5.0.0)
Requires-Dist: fake-useragent (>=1.1.3,<2.0.0)
Requires-Dist: pandas (>=1.5.0,<3.0.0)
Requires-Dist: requests (>=2.28.2,<3.0.0)
